APIFNLIB/__init__.py
APIFNLIB-1.0.1.dist-info/LICENCE.txt
APIFNLIB-1.0.1.dist-info/METADATA
APIFNLIB-1.0.1.dist-info/WHEEL
APIFNLIB-1.0.1.dist-info/top_level.txt
APIFNLIB-1.0.1.dist-info/RECORD
