Metadata-Version: 2.1
Name: APIFNLIB
Version: 1.0.1
Summary: Python LIB for FN-api.com
Home-page: UNKNOWN
Author: AquazDev
Author-email: 
License: UNKNOWN
Keywords: FN-LIb,fnapi.com,fortnite,fortnite cosmetics,Fn-api,Fnapi.com
Platform: UNKNOWN
Classifier: Programming Language :: Python :: 3
Classifier: License :: OSI Approved :: MIT License
Classifier: Operating System :: OS Independent
Requires-Python: >=3
License-File: LICENCE.txt
